llm_inference.py
llm_inference_cloud-0.1.dist-info/LICENSE
llm_inference_cloud-0.1.dist-info/METADATA
llm_inference_cloud-0.1.dist-info/WHEEL
llm_inference_cloud-0.1.dist-info/entry_points.txt
llm_inference_cloud-0.1.dist-info/top_level.txt
llm_inference_cloud-0.1.dist-info/RECORD
