Metadata-Version: 2.1
Name: llm-inference-cloud
Version: 0.1
Summary: LLM plugin for models hosted by Inference
Author: Nick Mystic
License: MIT
Project-URL: Homepage, https://github.com/ghostofpokemon/llm-inference
Project-URL: Changelog, https://github.com/ghostofpokemon/llm-inference/releases
Project-URL: Issues, https://github.com/ghostofpokemon/llm-inference/issues
Project-URL: CI, https://github.com/ghostofpokemon/llm-inference/actions
Classifier: License :: OSI Approved :: MIT License
License-File: LICENSE
Requires-Dist: llm>=0.8
Requires-Dist: httpx
Provides-Extra: test
Requires-Dist: pytest; extra == "test"
Requires-Dist: pytest-mock; extra == "test"
